Workbook
Name Slicer_Department: #N/A
Name Slicer_Education_Field: #N/A
Name Slicer_Gender: #N/A
Name Slicer_Job_Role: #N/A
Name Slicer_OverTime: #N/A

Sheet Raw_Data
A1: Age | B1: Attrition | C1: BusinessTravel | D1: DailyRate | E1: Department | F1: DistanceFromHome | G1: Education | H1: EducationField | I1: EmployeeCount | J1: EmployeeNumber | K1: EnvironmentSatisfaction | L1: Gender | M1: HourlyRate | N1: JobInvolvement | O1: JobLevel | P1: JobRole | Q1: JobSatisfaction | R1: MaritalStatus | S1: MonthlyIncome | T1: MonthlyRate | U1: NumCompaniesWorked | V1: Over18 | W1: OverTime | X1: PercentSalaryHike | Y1: PerformanceRating | Z1: RelationshipSatisfaction | AA1: StandardHours | AB1: StockOptionLevel | AC1: TotalWorkingYears | AD1: TrainingTimesLastYear | AE1: WorkLifeBalance | AF1: YearsAtCompany | AG1: YearsInCurrentRole | AH1: YearsSinceLastPromotion | AI1: YearsWithCurrManager
A2: 41 | B2: Yes | C2: Travel_Rarely | D2: 1102 | E2: Sales | F2: 1 | G2: 2 | H2: Life Sciences | I2: 1 | J2: 1 | K2: 2 | L2: Female | M2: 94 | N2: 3 | O2: 2 | P2: Sales Executive | Q2: 4 | R2: Single | S2: 5993 | T2: 19479 | U2: 8 | V2: Y | W2: Yes | X2: 11 | Y2: 3 | Z2: 1 | AA2: 80 | AB2: 0 | AC2: 8 | AD2: 0 | AE2: 1 | AF2: 6 | AG2: 4 | AH2: 0 | AI2: 5
A3: 49 | B3: No | C3: Travel_Frequently | D3: 279 | E3: Research & Development | F3: 8 | G3: 1 | H3: Life Sciences | I3: 1 | J3: 2 | K3: 3 | L3: Male | M3: 61 | N3: 2 | O3: 2 | P3: Research Scientist | Q3: 2 | R3: Married | S3: 5130 | T3: 24907 | U3: 1 | V3: Y | W3: No | X3: 23 | Y3: 4 | Z3: 4 | AA3: 80 | AB3: 1 | AC3: 10 | AD3: 3 | AE3: 3 | AF3: 10 | AG3: 7 | AH3: 1 | AI3: 7
A4: 37 | B4: Yes | C4: Travel_Rarely | D4: 1373 | E4: Research & Development | F4: 2 | G4: 2 | H4: Other | I4: 1 | J4: 4 | K4: 4 | L4: Male | M4: 92 | N4: 2 | O4: 1 | P4: Laboratory Technician | Q4: 3 | R4: Single | S4: 2090 | T4: 2396 | U4: 6 | V4: Y | W4: Yes | X4: 15 | Y4: 3 | Z4: 2 | AA4: 80 | AB4: 0 | AC4: 7 | AD4: 3 | AE4: 3 | AF4: 0 | AG4: 0 | AH4: 0 | AI4: 0
A5: 33 | B5: No | C5: Travel_Frequently | D5: 1392 | E5: Research & Development | F5: 3 | G5: 4 | H5: Life Sciences | I5: 1 | J5: 5 | K5: 4 | L5: Female | M5: 56 | N5: 3 | O5: 1 | P5: Research Scientist | Q5: 3 | R5: Married | S5: 2909 | T5: 23159 | U5: 1 | V5: Y | W5: Yes | X5: 11 | Y5: 3 | Z5: 3 | AA5: 80 | AB5: 0 | AC5: 8 | AD5: 3 | AE5: 3 | AF5: 8 | AG5: 7 | AH5: 3 | AI5: 0
A6: 27 | B6: No | C6: Travel_Rarely | D6: 591 | E6: Research & Development | F6: 2 | G6: 1 | H6: Medical | I6: 1 | J6: 7 | K6: 1 | L6: Male | M6: 40 | N6: 3 | O6: 1 | P6: Laboratory Technician | Q6: 2 | R6: Married | S6: 3468 | T6: 16632 | U6: 9 | V6: Y | W6: No | X6: 12 | Y6: 3 | Z6: 4 | AA6: 80 | AB6: 1 | AC6: 6 | AD6: 3 | AE6: 3 | AF6: 2 | AG6: 2 | AH6: 2 | AI6: 2
A7: 32 | B7: No | C7: Travel_Frequently | D7: 1005 | E7: Research & Development | F7: 2 | G7: 2 | H7: Life Sciences | I7: 1 | J7: 8 | K7: 4 | L7: Male | M7: 79 | N7: 3 | O7: 1 | P7: Laboratory Technician | Q7: 4 | R7: Single | S7: 3068 | T7: 11864 | U7: 0 | V7: Y | W7: No | X7: 13 | Y7: 3 | Z7: 3 | AA7: 80 | AB7: 0 | AC7: 8 | AD7: 2 | AE7: 2 | AF7: 7 | AG7: 7 | AH7: 3 | AI7: 6
A8: 59 | B8: No | C8: Travel_Rarely | D8: 1324 | E8: Research & Development | F8: 3 | G8: 3 | H8: Medical | I8: 1 | J8: 10 | K8: 3 | L8: Female | M8: 81 | N8: 4 | O8: 1 | P8: Laboratory Technician | Q8: 1 | R8: Married | S8: 2670 | T8: 9964 | U8: 4 | V8: Y | W8: Yes | X8: 20 | Y8: 4 | Z8: 1 | AA8: 80 | AB8: 3 | AC8: 12 | AD8: 3 | AE8: 2 | AF8: 1 | AG8: 0 | AH8: 0 | AI8: 0
A9: 30 | B9: No | C9: Travel_Rarely | D9: 1358 | E9: Research & Development | F9: 24 | G9: 1 | H9: Life Sciences | I9: 1 | J9: 11 | K9: 4 | L9: Male | M9: 67 | N9: 3 | O9: 1 | P9: Laboratory Technician | Q9: 3 | R9: Divorced | S9: 2693 | T9: 13335 | U9: 1 | V9: Y | W9: No | X9: 22 | Y9: 4 | Z9: 2 | AA9: 80 | AB9: 1 | AC9: 1 | AD9: 2 | AE9: 3 | AF9: 1 | AG9: 0 | AH9: 0 | AI9: 0
A10: 38 | B10: No | C10: Travel_Frequently | D10: 216 | E10: Research & Development | F10: 23 | G10: 3 | H10: Life Sciences | I10: 1 | J10: 12 | K10: 4 | L10: Male | M10: 44 | N10: 2 | O10: 3 | P10: Manufacturing Director | Q10: 3 | R10: Single | S10: 9526 | T10: 8787 | U10: 0 | V10: Y | W10: No | X10: 21 | Y10: 4 | Z10: 2 | AA10: 80 | AB10: 0 | AC10: 10 | AD10: 2 | AE10: 3 | AF10: 9 | AG10: 7 | AH10: 1 | AI10: 8
A11: 36 | B11: No | C11: Travel_Rarely | D11: 1299 | E11: Research & Development | F11: 27 | G11: 3 | H11: Medical | I11: 1 | J11: 13 | K11: 3 | L11: Male | M11: 94 | N11: 3 | O11: 2 | P11: Healthcare Representative | Q11: 3 | R11: Married | S11: 5237 | T11: 16577 | U11: 6 | V11: Y | W11: No | X11: 13 | Y11: 3 | Z11: 2 | AA11: 80 | AB11: 2 | AC11: 17 | AD11: 3 | AE11: 2 | AF11: 7 | AG11: 7 | AH11: 7 | AI11: 7
A12: 35 | B12: No | C12: Travel_Rarely | D12: 809 | E12: Research & Development | F12: 16 | G12: 3 | H12: Medical | I12: 1 | J12: 14 | K12: 1 | L12: Male | M12: 84 | N12: 4 | O12: 1 | P12: Laboratory Technician | Q12: 2 | R12: Married | S12: 2426 | T12: 16479 | U12: 0 | V12: Y | W12: No | X12: 13 | Y12: 3 | Z12: 3 | AA12: 80 | AB12: 1 | AC12: 6 | AD12: 5 | AE12: 3 | AF12: 5 | AG12: 4 | AH12: 0 | AI12: 3
A13: 29 | B13: No | C13: Travel_Rarely | D13: 153 | E13: Research & Development | F13: 15 | G13: 2 | H13: Life Sciences | I13: 1 | J13: 15 | K13: 4 | L13: Female | M13: 49 | N13: 2 | O13: 2 | P13: Laboratory Technician | Q13: 3 | R13: Single | S13: 4193 | T13: 12682 | U13: 0 | V13: Y | W13: Yes | X13: 12 | Y13: 3 | Z13: 4 | AA13: 80 | AB13: 0 | AC13: 10 | AD13: 3 | AE13: 3 | AF13: 9 | AG13: 5 | AH13: 0 | AI13: 8
... A1471: 34 | B1471: No | C1471: Travel_Rarely | D1471: 628 | E1471: Research & Development | F1471: 8 | G1471: 3 | H1471: Medical | I1471: 1 | J1471: 2068 | K1471: 2 | L1471: Male | M1471: 82 | N1471: 4 | O1471: 2 | P1471: Laboratory Technician | Q1471: 3 | R1471: Married | S1471: 4404 | T1471: 10228 | U1471: 2 | V1471: Y | W1471: No | X1471: 12 | Y1471: 3 | Z1471: 1 | AA1471: 80 | AB1471: 0 | AC1471: 6 | AD1471: 3 | AE1471: 4 | AF1471: 4 | AG1471: 3 | AH1471: 1 | AI1471: 2

Sheet Clean_Data
A1: Age | B1: Attrition | C1: Business_Travel | D1: Daily_Rate | E1: Department | F1: Distance_From_Home | G1: Education | H1: Education_Field | I1: Employee_Count | J1: Employee_Number | K1: Environment_Satisfaction | L1: Gender | M1: Hourly_Rate | N1: Job_Involvement | O1: Job_Level | P1: Job_Role | Q1: Job_Satisfaction | R1: Marital_Status | S1: Monthly_Income | T1: Monthly_Rate | U1: Num_Companies_Worked | V1: Over_18 | W1: OverTime | X1: Percent_Salary_Hike | Y1: Performance_Rating | Z1: Relationship_Satisfaction | AA1: Standard_Hours | AB1: Stock_Option_Level | AC1: Total_Working_Years | AD1: Training_Times_Last_Year | AE1: Work_Life_Balance | AF1: Years_At_Company | AG1: Years_In_Current_Role | AH1: Years_Since_Last_Promotion | AI1: Years_With_Curr_Manager | AJ1: Age_Group | AK1: Income_Band | AL1: Years_at_Company_Band | AM1: Attrition Status
A2: 41 | B2: Yes | C2: Travel_Rarely | D2: 1102 | E2: Sales | F2: 1 | G2: 2 | H2: Life Sciences | I2: 1 | J2: 1 | K2: 2 | L2: Female | M2: 94 | N2: 3 | O2: 2 | P2: Sales Executive | Q2: 4 | R2: Single | S2: 5993 | T2: 19479 | U2: 8 | V2: Y | W2: Yes | X2: 11 | Y2: 3 | Z2: 1 | AA2: 80 | AB2: 0 | AC2: 8 | AD2: 0 | AE2: 1 | AF2: 6 | AG2: 4 | AH2: 0 | AI2: 5 | AJ2: =IF(A2<=25,"18-25",IF(A2<=35,"26-35",IF(A2<=45,"36-45",IF(A2<=55,"46-55","56+")))) -> 36-45 | AK2: =IF(S2<3000,"Low",IF(S2<7000,"Medium","High")) -> Medium | AL2: =IF(AF1<=2,"0-2",IF(AF1<=5,"3-5",IF(AF1<=10,"6-10","11+"))) -> 11+ | AM2: =IF(B1="Yes","Left","Stayed") -> Stayed
A3: 49 | B3: No | C3: Travel_Frequently | D3: 279 | E3: Research & Development | F3: 8 | G3: 1 | H3: Life Sciences | I3: 1 | J3: 2 | K3: 3 | L3: Male | M3: 61 | N3: 2 | O3: 2 | P3: Research Scientist | Q3: 2 | R3: Married | S3: 5130 | T3: 24907 | U3: 1 | V3: Y | W3: No | X3: 23 | Y3: 4 | Z3: 4 | AA3: 80 | AB3: 1 | AC3: 10 | AD3: 3 | AE3: 3 | AF3: 10 | AG3: 7 | AH3: 1 | AI3: 7 | AJ3: =IF(A3<=25,"18-25",IF(A3<=35,"26-35",IF(A3<=45,"36-45",IF(A3<=55,"46-55","56+")))) -> 46-55 | AK3: =IF(S3<3000,"Low",IF(S3<7000,"Medium","High")) -> Medium | AL3: =IF(AF2<=2,"0-2",IF(AF2<=5,"3-5",IF(AF2<=10,"6-10","11+"))) -> 6-10 | AM3: =IF(B2="Yes","Left","Stayed") -> Left
A4: 37 | B4: Yes | C4: Travel_Rarely | D4: 1373 | E4: Research & Development | F4: 2 | G4: 2 | H4: Other | I4: 1 | J4: 4 | K4: 4 | L4: Male | M4: 92 | N4: 2 | O4: 1 | P4: Laboratory Technician | Q4: 3 | R4: Single | S4: 2090 | T4: 2396 | U4: 6 | V4: Y | W4: Yes | X4: 15 | Y4: 3 | Z4: 2 | AA4: 80 | AB4: 0 | AC4: 7 | AD4: 3 | AE4: 3 | AF4: 0 | AG4: 0 | AH4: 0 | AI4: 0 | AJ4: =IF(A4<=25,"18-25",IF(A4<=35,"26-35",IF(A4<=45,"36-45",IF(A4<=55,"46-55","56+")))) -> 36-45 | AK4: =IF(S4<3000,"Low",IF(S4<7000,"Medium","High")) -> Low | AL4: =IF(AF3<=2,"0-2",IF(AF3<=5,"3-5",IF(AF3<=10,"6-10","11+"))) -> 6-10 | AM4: =IF(B3="Yes","Left","Stayed") -> Stayed
A5: 33 | B5: No | C5: Travel_Frequently | D5: 1392 | E5: Research & Development | F5: 3 | G5: 4 | H5: Life Sciences | I5: 1 | J5: 5 | K5: 4 | L5: Female | M5: 56 | N5: 3 | O5: 1 | P5: Research Scientist | Q5: 3 | R5: Married | S5: 2909 | T5: 23159 | U5: 1 | V5: Y | W5: Yes | X5: 11 | Y5: 3 | Z5: 3 | AA5: 80 | AB5: 0 | AC5: 8 | AD5: 3 | AE5: 3 | AF5: 8 | AG5: 7 | AH5: 3 | AI5: 0 | AJ5: =IF(A5<=25,"18-25",IF(A5<=35,"26-35",IF(A5<=45,"36-45",IF(A5<=55,"46-55","56+")))) -> 26-35 | AK5: =IF(S5<3000,"Low",IF(S5<7000,"Medium","High")) -> Low | AL5: =IF(AF4<=2,"0-2",IF(AF4<=5,"3-5",IF(AF4<=10,"6-10","11+"))) -> 0-2 | AM5: =IF(B4="Yes","Left","Stayed") -> Left
A6: 27 | B6: No | C6: Travel_Rarely | D6: 591 | E6: Research & Development | F6: 2 | G6: 1 | H6: Medical | I6: 1 | J6: 7 | K6: 1 | L6: Male | M6: 40 | N6: 3 | O6: 1 | P6: Laboratory Technician | Q6: 2 | R6: Married | S6: 3468 | T6: 16632 | U6: 9 | V6: Y | W6: No | X6: 12 | Y6: 3 | Z6: 4 | AA6: 80 | AB6: 1 | AC6: 6 | AD6: 3 | AE6: 3 | AF6: 2 | AG6: 2 | AH6: 2 | AI6: 2 | AJ6: =IF(A6<=25,"18-25",IF(A6<=35,"26-35",IF(A6<=45,"36-45",IF(A6<=55,"46-55","56+")))) -> 26-35 | AK6: =IF(S6<3000,"Low",IF(S6<7000,"Medium","High")) -> Medium | AL6: =IF(AF5<=2,"0-2",IF(AF5<=5,"3-5",IF(AF5<=10,"6-10","11+"))) -> 6-10 | AM6: =IF(B5="Yes","Left","Stayed") -> Stayed
A7: 32 | B7: No | C7: Travel_Frequently | D7: 1005 | E7: Research & Development | F7: 2 | G7: 2 | H7: Life Sciences | I7: 1 | J7: 8 | K7: 4 | L7: Male | M7: 79 | N7: 3 | O7: 1 | P7: Laboratory Technician | Q7: 4 | R7: Single | S7: 3068 | T7: 11864 | U7: 0 | V7: Y | W7: No | X7: 13 | Y7: 3 | Z7: 3 | AA7: 80 | AB7: 0 | AC7: 8 | AD7: 2 | AE7: 2 | AF7: 7 | AG7: 7 | AH7: 3 | AI7: 6 | AJ7: =IF(A7<=25,"18-25",IF(A7<=35,"26-35",IF(A7<=45,"36-45",IF(A7<=55,"46-55","56+")))) -> 26-35 | AK7: =IF(S7<3000,"Low",IF(S7<7000,"Medium","High")) -> Medium | AL7: =IF(AF6<=2,"0-2",IF(AF6<=5,"3-5",IF(AF6<=10,"6-10","11+"))) -> 0-2 | AM7: =IF(B6="Yes","Left","Stayed") -> Stayed
A8: 59 | B8: No | C8: Travel_Rarely | D8: 1324 | E8: Research & Development | F8: 3 | G8: 3 | H8: Medical | I8: 1 | J8: 10 | K8: 3 | L8: Female | M8: 81 | N8: 4 | O8: 1 | P8: Laboratory Technician | Q8: 1 | R8: Married | S8: 2670 | T8: 9964 | U8: 4 | V8: Y | W8: Yes | X8: 20 | Y8: 4 | Z8: 1 | AA8: 80 | AB8: 3 | AC8: 12 | AD8: 3 | AE8: 2 | AF8: 1 | AG8: 0 | AH8: 0 | AI8: 0 | AJ8: =IF(A8<=25,"18-25",IF(A8<=35,"26-35",IF(A8<=45,"36-45",IF(A8<=55,"46-55","56+")))) -> 56+ | AK8: =IF(S8<3000,"Low",IF(S8<7000,"Medium","High")) -> Low | AL8: =IF(AF7<=2,"0-2",IF(AF7<=5,"3-5",IF(AF7<=10,"6-10","11+"))) -> 6-10 | AM8: =IF(B7="Yes","Left","Stayed") -> Stayed
A9: 30 | B9: No | C9: Travel_Rarely | D9: 1358 | E9: Research & Development | F9: 24 | G9: 1 | H9: Life Sciences | I9: 1 | J9: 11 | K9: 4 | L9: Male | M9: 67 | N9: 3 | O9: 1 | P9: Laboratory Technician | Q9: 3 | R9: Divorced | S9: 2693 | T9: 13335 | U9: 1 | V9: Y | W9: No | X9: 22 | Y9: 4 | Z9: 2 | AA9: 80 | AB9: 1 | AC9: 1 | AD9: 2 | AE9: 3 | AF9: 1 | AG9: 0 | AH9: 0 | AI9: 0 | AJ9: =IF(A9<=25,"18-25",IF(A9<=35,"26-35",IF(A9<=45,"36-45",IF(A9<=55,"46-55","56+")))) -> 26-35 | AK9: =IF(S9<3000,"Low",IF(S9<7000,"Medium","High")) -> Low | AL9: =IF(AF8<=2,"0-2",IF(AF8<=5,"3-5",IF(AF8<=10,"6-10","11+"))) -> 0-2 | AM9: =IF(B8="Yes","Left","Stayed") -> Stayed
A10: 38 | B10: No | C10: Travel_Frequently | D10: 216 | E10: Research & Development | F10: 23 | G10: 3 | H10: Life Sciences | I10: 1 | J10: 12 | K10: 4 | L10: Male | M10: 44 | N10: 2 | O10: 3 | P10: Manufacturing Director | Q10: 3 | R10: Single | S10: 9526 | T10: 8787 | U10: 0 | V10: Y | W10: No | X10: 21 | Y10: 4 | Z10: 2 | AA10: 80 | AB10: 0 | AC10: 10 | AD10: 2 | AE10: 3 | AF10: 9 | AG10: 7 | AH10: 1 | AI10: 8 | AJ10: =IF(A10<=25,"18-25",IF(A10<=35,"26-35",IF(A10<=45,"36-45",IF(A10<=55,"46-55","56+")))) -> 36-45 | AK10: =IF(S10<3000,"Low",IF(S10<7000,"Medium","High")) -> High | AL10: =IF(AF9<=2,"0-2",IF(AF9<=5,"3-5",IF(AF9<=10,"6-10","11+"))) -> 0-2 | AM10: =IF(B9="Yes","Left","Stayed") -> Stayed
A11: 36 | B11: No | C11: Travel_Rarely | D11: 1299 | E11: Research & Development | F11: 27 | G11: 3 | H11: Medical | I11: 1 | J11: 13 | K11: 3 | L11: Male | M11: 94 | N11: 3 | O11: 2 | P11: Healthcare Representative | Q11: 3 | R11: Married | S11: 5237 | T11: 16577 | U11: 6 | V11: Y | W11: No | X11: 13 | Y11: 3 | Z11: 2 | AA11: 80 | AB11: 2 | AC11: 17 | AD11: 3 | AE11: 2 | AF11: 7 | AG11: 7 | AH11: 7 | AI11: 7 | AJ11: =IF(A11<=25,"18-25",IF(A11<=35,"26-35",IF(A11<=45,"36-45",IF(A11<=55,"46-55","56+")))) -> 36-45 | AK11: =IF(S11<3000,"Low",IF(S11<7000,"Medium","High")) -> Medium | AL11: =IF(AF10<=2,"0-2",IF(AF10<=5,"3-5",IF(AF10<=10,"6-10","11+"))) -> 6-10 | AM11: =IF(B10="Yes","Left","Stayed") -> Stayed
A12: 35 | B12: No | C12: Travel_Rarely | D12: 809 | E12: Research & Development | F12: 16 | G12: 3 | H12: Medical | I12: 1 | J12: 14 | K12: 1 | L12: Male | M12: 84 | N12: 4 | O12: 1 | P12: Laboratory Technician | Q12: 2 | R12: Married | S12: 2426 | T12: 16479 | U12: 0 | V12: Y | W12: No | X12: 13 | Y12: 3 | Z12: 3 | AA12: 80 | AB12: 1 | AC12: 6 | AD12: 5 | AE12: 3 | AF12: 5 | AG12: 4 | AH12: 0 | AI12: 3 | AJ12: =IF(A12<=25,"18-25",IF(A12<=35,"26-35",IF(A12<=45,"36-45",IF(A12<=55,"46-55","56+")))) -> 26-35 | AK12: =IF(S12<3000,"Low",IF(S12<7000,"Medium","High")) -> Low | AL12: =IF(AF11<=2,"0-2",IF(AF11<=5,"3-5",IF(AF11<=10,"6-10","11+"))) -> 6-10 | AM12: =IF(B11="Yes","Left","Stayed") -> Stayed
A13: 29 | B13: No | C13: Travel_Rarely | D13: 153 | E13: Research & Development | F13: 15 | G13: 2 | H13: Life Sciences | I13: 1 | J13: 15 | K13: 4 | L13: Female | M13: 49 | N13: 2 | O13: 2 | P13: Laboratory Technician | Q13: 3 | R13: Single | S13: 4193 | T13: 12682 | U13: 0 | V13: Y | W13: Yes | X13: 12 | Y13: 3 | Z13: 4 | AA13: 80 | AB13: 0 | AC13: 10 | AD13: 3 | AE13: 3 | AF13: 9 | AG13: 5 | AH13: 0 | AI13: 8 | AJ13: =IF(A13<=25,"18-25",IF(A13<=35,"26-35",IF(A13<=45,"36-45",IF(A13<=55,"46-55","56+")))) -> 26-35 | AK13: =IF(S13<3000,"Low",IF(S13<7000,"Medium","High")) -> Medium | AL13: =IF(AF12<=2,"0-2",IF(AF12<=5,"3-5",IF(AF12<=10,"6-10","11+"))) -> 3-5 | AM13: =IF(B12="Yes","Left","Stayed") -> Stayed
... A1471: 34 | B1471: No | C1471: Travel_Rarely | D1471: 628 | E1471: Research & Development | F1471: 8 | G1471: 3 | H1471: Medical | I1471: 1 | J1471: 2068 | K1471: 2 | L1471: Male | M1471: 82 | N1471: 4 | O1471: 2 | P1471: Laboratory Technician | Q1471: 3 | R1471: Married | S1471: 4404 | T1471: 10228 | U1471: 2 | V1471: Y | W1471: No | X1471: 12 | Y1471: 3 | Z1471: 1 | AA1471: 80 | AB1471: 0 | AC1471: 6 | AD1471: 3 | AE1471: 4 | AF1471: 4 | AG1471: 3 | AH1471: 1 | AI1471: 2 | AJ1471: =IF(A1471<=25,"18-25",IF(A1471<=35,"26-35",IF(A1471<=45,"36-45",IF(A1471<=55,"46-55","56+")))) -> 26-35 | AK1471: =IF(S1471<3000,"Low",IF(S1471<7000,"Medium","High")) -> Medium | AL1471: =IF(AF1470<=2,"0-2",IF(AF1470<=5,"3-5",IF(AF1470<=10,"6-10","11+"))) -> 6-10 | AM1471: =IF(B1470="Yes","Left","Stayed") -> Stayed

Sheet Pivot_Tables
A6: Attrition | B6: Count of Employee_Number | D6: Count of Employee_Number | E6: Column Labels | I6: Count of Employee_Number | J6: Column Labels
A7: No | B7: 1233 | D7: Row Labels | E7: No | F7: Yes | G7: Grand Total | I7: Row Labels | J7: No | K7: Yes | L7: Grand Total
A8: Yes | B8: 237 | D8: Human Resources | E8: 51 | F8: 12 | G8: 63 | I8: Female | J8: 501 | K8: 87 | L8: 588
A9: Grand Total | B9: 1470 | D9: Research & Development | E9: 828 | F9: 133 | G9: 961 | I9: Male | J9: 732 | K9: 150 | L9: 882
D10: Sales | E10: 354 | F10: 92 | G10: 446 | I10: Grand Total | J10: 1233 | K10: 237 | L10: 1470
D11: Grand Total | E11: 1233 | F11: 237 | G11: 1470
A17: Count of Employee_Number | B17: Column Labels | K17: Count of Employee_Number | L17: Column Labels
A18: Row Labels | B18: No | C18: Yes | D18: Grand Total | F18: Count of Employee_Number | G18: Column Labels | K18: Row Labels | L18: No | M18: Yes | N18: Grand Total
A19: Healthcare Representative | B19: 122 | C19: 9 | D19: 131 | F19: Row Labels | G19: No | H19: Yes | I19: Grand Total | K19: High | L19: 388 | M19: 47 | N19: 435
A20: Human Resources | B20: 40 | C20: 12 | D20: 52 | F20: 18-25 | G20: 79 | H20: 44 | I20: 123 | K20: Low | L20: 282 | M20: 113 | N20: 395
A21: Laboratory Technician | B21: 197 | C21: 62 | D21: 259 | F21: 26-35 | G21: 490 | H21: 116 | I21: 606 | K21: Medium | L21: 563 | M21: 77 | N21: 640
A22: Manager | B22: 97 | C22: 5 | D22: 102 | F22: 36-45 | G22: 425 | H22: 43 | I22: 468 | K22: Grand Total | L22: 1233 | M22: 237 | N22: 1470
A23: Manufacturing Director | B23: 135 | C23: 10 | D23: 145 | F23: 46-55 | G23: 200 | H23: 26 | I23: 226
A24: Research Director | B24: 78 | C24: 2 | D24: 80 | F24: 56+ | G24: 39 | H24: 8 | I24: 47
A25: Research Scientist | B25: 245 | C25: 47 | D25: 292 | F25: Grand Total | G25: 1233 | H25: 237 | I25: 1470
A26: Sales Executive | B26: 269 | C26: 57 | D26: 326
A27: Sales Representative | B27: 50 | C27: 33 | D27: 83
A28: Grand Total | B28: 1233 | C28: 237 | D28: 1470
K31: Count of Employee_Number | L31: Column Labels
F32: Count of Employee_Number | G32: Column Labels | K32: Row Labels | L32: No | M32: Yes | N32: Grand Total
F33: Row Labels | G33: No | H33: Yes | I33: Grand Total | K33: 1 | L33: 55 | M33: 25 | N33: 80
A34: Count of Employee_Number | B34: Column Labels | F34: Human Resources | G34: 20 | H34: 7 | I34: 27 | K34: 2 | L34: 286 | M34: 58 | N34: 344
A35: Row Labels | B35: No | C35: Yes | D35: Grand Total | F35: Life Sciences | G35: 517 | H35: 89 | I35: 606 | K35: 3 | L35: 766 | M35: 127 | N35: 893
A36: No | B36: 944 | C36: 110 | D36: 1054 | F36: Marketing | G36: 124 | H36: 35 | I36: 159 | K36: 4 | L36: 126 | M36: 27 | N36: 153
A37: Yes | B37: 289 | C37: 127 | D37: 416 | F37: Medical | G37: 401 | H37: 63 | I37: 464 | K37: Grand Total | L37: 1233 | M37: 237 | N37: 1470
A38: Grand Total | B38: 1233 | C38: 237 | D38: 1470 | F38: Other | G38: 71 | H38: 11 | I38: 82
F39: Technical Degree | G39: 100 | H39: 32 | I39: 132
F40: Grand Total | G40: 1233 | H40: 237 | I40: 1470
F55: Row Labels | G55: Count of Employee_Number | H55: Average of Age | I55: Average of Monthly_Income
F56: No | G56: 1233 | H56: 37.561233 | I56: 6832.7397
F57: Yes | G57: 237 | H57: 33.607595 | I57: 4787.0928
F58: Grand Total | G58: 1470 | H58: 36.92381 | I58: 6502.9313

Sheet Analysis
A1: A | B1: B
A2: KPI | B2: Value
A3: Total Employees | B3: =GETPIVOTDATA("Count of Employee_Number",Pivot_Tables!$F$55) -> 1470
A4: Employees Who Left | B4: =GETPIVOTDATA("Count of Employee_Number",Pivot_Tables!$F$55,"Attrition","Yes") -> 237
A5: Active Employees | B5: =GETPIVOTDATA("Count of Employee_Number",Pivot_Tables!$F$55,"Attrition","No") -> 1233
A6: Attrition Rate | B6: =B4/B3 -> 0.16122449
A7: Average Age | B7: =GETPIVOTDATA("Average of Age",Pivot_Tables!$F$55) -> 36.92381
A8: Average Monthly Income | B8: =GETPIVOTDATA("Average of Monthly_Income",Pivot_Tables!$F$55) -> 6502.9313

Sheet Dashboard
